ticktick_mcp/__init__.py
ticktick_mcp/authenticate.py
ticktick_mcp/cli.py
ticktick_mcp/src/__init__.py
ticktick_mcp/src/auth.py
ticktick_mcp/src/server.py
ticktick_mcp/src/ticktick_client.py
iflow_mcp_ticktick_mcp-0.1.0.dist-info/METADATA
iflow_mcp_ticktick_mcp-0.1.0.dist-info/WHEEL
iflow_mcp_ticktick_mcp-0.1.0.dist-info/entry_points.txt
iflow_mcp_ticktick_mcp-0.1.0.dist-info/top_level.txt
iflow_mcp_ticktick_mcp-0.1.0.dist-info/RECORD
