Metadata-Version: 2.4
Name: iflow-mcp_ticktick-mcp
Version: 0.1.0
Summary: Model Context Protocol (MCP) server for TickTick task management
Home-page: https://github.com/iflow-mcp/jacepark12-ticktick-mcp
Author: Jaesung Park
Author-email: parkjs814@gmail.com
Classifier: Development Status :: 3 - Alpha
Classifier: Intended Audience :: Developers
Classifier: License :: OSI Approved :: MIT License
Classifier: Programming Language :: Python :: 3
Classifier: Programming Language :: Python :: 3.10
Classifier: Programming Language :: Python :: 3.11
Classifier: Programming Language :: Python :: 3.12
Requires-Python: >=3.10
Requires-Dist: mcp[cli]<2.0.0,>=1.2.0
Requires-Dist: python-dotenv<2.0.0,>=1.0.0
Requires-Dist: requests<3.0.0,>=2.30.0
Dynamic: author
Dynamic: author-email
Dynamic: classifier
Dynamic: home-page
Dynamic: requires-dist
Dynamic: requires-python
Dynamic: summary
